Metadata-Version: 2.1
Name: monitor-logs
Version: 0.1.3
Summary: Monitor your logs from anywhere
Home-page: https://github.com/Vinithavn/Monitor-model-logs/
